oak_common/__init__.py
oak_common/__version__.py
oak_common/oak_common.py
oak_common-0.0.5.dist-info/METADATA
oak_common-0.0.5.dist-info/WHEEL
oak_common-0.0.5.dist-info/top_level.txt
oak_common-0.0.5.dist-info/RECORD
