Metadata-Version: 2.1
Name: oak-common
Version: 0.0.5
Summary: 包含了获取交易日,日行情/指数行情等接口
Home-page: 
Author: jinsz/zhouzt
Author-email: jinshuzhao@oak-amc.com
Classifier: Programming Language :: Python :: 3
Classifier: License :: OSI Approved :: MIT License
Classifier: Operating System :: OS Independent
Requires-Python: >=3.6
